{"config":{"lookback_days":252,"min_gain_percent":18,"min_green_candles":2,"surge_recency_days":45,"min_drop_percent":0.1,"min_breakdown_volume_ratio":0.5,"ema_period":9,"price_proximity_percent":1,"sell_zone_lookback_days":10,"expiry_mode":"auto","min_days_to_expiry":5,"premium_vol_surge_threshold":1.5},"years_tested":10,"aggregate":{"tickers":["HFCL"],"total_trades":29,"wins":21,"losses":8,"accuracy_pct":72.4,"total_pnl":16.69,"avg_pnl":0.58,"premium_analysis":{"threshold":1.5,"high_vol_cohort":{"trades":29,"wins":21,"losses":8,"accuracy_pct":72.4,"avg_premium":1.58,"avg_pnl":0.58,"avg_prem_score":4.21},"normal_cohort":{"trades":0,"wins":0,"losses":0,"accuracy_pct":null,"avg_premium":null,"avg_pnl":null,"avg_prem_score":null}},"dual_expiry_comparison":{"current_month":{"trades":27,"wins":21,"losses":6,"accuracy_pct":77.8,"avg_premium":1.22,"avg_pnl":0.73,"total_pnl":19.81},"next_month":{"trades":29,"wins":17,"losses":12,"accuracy_pct":58.6,"avg_premium":3.34,"avg_pnl":0.69,"total_pnl":19.88}}},"per_ticker":[{"ticker":"HFCL","summary":{"total_trades":29,"wins":21,"losses":8,"accuracy_pct":72.4,"avg_pnl_per_unit":0.58,"avg_premium":1.58,"total_pnl":16.69,"premium_analysis":{"threshold":1.5,"high_vol_cohort":{"trades":29,"wins":21,"losses":8,"accuracy_pct":72.4,"avg_premium":1.58,"avg_pnl":0.58,"avg_prem_score":4.21},"normal_cohort":{"trades":0,"wins":0,"losses":0,"accuracy_pct":null,"avg_premium":null,"avg_pnl":null,"avg_prem_score":null}},"dual_expiry_comparison":{"current_month":{"trades":27,"wins":21,"losses":6,"accuracy_pct":77.8,"avg_premium":1.22,"avg_pnl":0.73,"total_pnl":19.81},"next_month":{"trades":29,"wins":17,"losses":12,"accuracy_pct":58.6,"avg_premium":3.34,"avg_pnl":0.69,"total_pnl":19.88}}},"trades":[{"entry_date":"2017-07-21","expiry_date":"2017-07-27","actual_data_date":"2017-07-27","entry_price":16.8,"surge_high":16.95,"strike":20,"entry_ce_premium":0.01,"expiry_close":17.1,"intrinsic_value":0.0,"iv_sigma":61.9,"T_days":6,"expiry_mode":"auto","expiry_label":"auto","result":"WIN","pnl_per_unit":0.01,"return_pct":100.0,"vol_at_g3":21112656,"avg_vol_20d_g3":3884407,"vol_surge_at_g3":5.44,"premium_score":0.05,"is_high_prem":true,"ticker":"HFCL","gate1_date":"2017-04-27","gate2_date":"2017-05-02","gate3_date":"2017-07-21","surge_gain_pct":18.84,"surge_candles":5,"volume_ratio":0.51,"cur_expiry":{"expiry_date":"2017-07-27","actual_data_date":"2017-07-27","T_days":6,"entry_ce_premium":0.01,"expiry_close":17.1,"intrinsic_value":0.0,"result":"WIN","pnl_per_unit":0.01,"return_pct":100.0},"nxt_expiry":{"expiry_date":"2017-08-31","actual_data_date":"2017-08-31","T_days":41,"entry_ce_premium":0.45,"expiry_close":17.95,"intrinsic_value":0.0,"result":"WIN","pnl_per_unit":0.45,"return_pct":100.0}},{"entry_date":"2017-08-28","expiry_date":"2017-09-28","actual_data_date":"2017-09-28","entry_price":17.5,"surge_high":19.15,"strike":20,"entry_ce_premium":0.54,"expiry_close":25.35,"intrinsic_value":5.35,"iv_sigma":65.9,"T_days":31,"expiry_mode":"auto","expiry_label":"auto","result":"LOSS","pnl_per_unit":-1.62,"return_pct":-300.0,"vol_at_g3":13337888,"avg_vol_20d_g3":6776856,"vol_surge_at_g3":1.97,"premium_score":1.06,"is_high_prem":true,"ticker":"HFCL","gate1_date":"2017-07-11","gate2_date":"2017-08-03","gate3_date":"2017-08-28","surge_gain_pct":28.57,"surge_candles":4,"volume_ratio":2.45,"cur_expiry":{"expiry_date":"2017-08-31","actual_data_date":"2017-08-31","T_days":3,"entry_ce_premium":0.01,"expiry_close":17.95,"intrinsic_value":0.0,"result":"WIN","pnl_per_unit":0.01,"return_pct":100.0},"nxt_expiry":{"expiry_date":"2017-09-28","actual_data_date":"2017-09-28","T_days":31,"entry_ce_premium":0.54,"expiry_close":25.35,"intrinsic_value":5.35,"result":"LOSS","pnl_per_unit":-1.62,"return_pct":-300.0}},{"entry_date":"2018-01-10","expiry_date":"2018-01-25","actual_data_date":"2018-01-25","entry_price":35.2,"surge_high":35.95,"strike":40,"entry_ce_premium":0.37,"expiry_close":30.75,"intrinsic_value":0.0,"iv_sigma":60.9,"T_days":15,"expiry_mode":"auto","expiry_label":"auto","result":"WIN","pnl_per_unit":0.37,"return_pct":100.0,"vol_at_g3":40467813,"avg_vol_20d_g3":11796589,"vol_surge_at_g3":3.43,"premium_score":1.27,"is_high_prem":true,"ticker":"HFCL","gate1_date":"2017-08-29","gate2_date":"2017-09-25","gate3_date":"2018-01-10","surge_gain_pct":28.57,"surge_candles":4,"volume_ratio":0.8,"cur_expiry":{"expiry_date":"2018-01-25","actual_data_date":"2018-01-25","T_days":15,"entry_ce_premium":0.37,"expiry_close":30.75,"intrinsic_value":0.0,"result":"WIN","pnl_per_unit":0.37,"return_pct":100.0},"nxt_expiry":{"expiry_date":"2018-02-22","actual_data_date":"2018-02-22","T_days":43,"entry_ce_premium":1.37,"expiry_close":27.9,"intrinsic_value":0.0,"result":"WIN","pnl_per_unit":1.37,"return_pct":100.0}},{"entry_date":"2021-05-10","expiry_date":"2021-05-27","actual_data_date":"2021-05-27","entry_price":34.5,"surge_high":36.65,"strike":40,"entry_ce_premium":0.44,"expiry_close":46.8,"intrinsic_value":6.8,"iv_sigma":66.6,"T_days":17,"expiry_mode":"auto","expiry_label":"auto","result":"LOSS","pnl_per_unit":-1.32,"return_pct":-300.0,"vol_at_g3":47351180,"avg_vol_20d_g3":10058097,"vol_surge_at_g3":4.71,"premium_score":2.07,"is_high_prem":true,"ticker":"HFCL","gate1_date":"2018-01-05","gate2_date":"2018-01-16","gate3_date":"2021-05-10","surge_gain_pct":18.32,"surge_candles":2,"volume_ratio":0.93,"cur_expiry":{"expiry_date":"2021-05-27","actual_data_date":"2021-05-27","T_days":17,"entry_ce_premium":0.44,"expiry_close":46.8,"intrinsic_value":6.8,"result":"LOSS","pnl_per_unit":-1.32,"return_pct":-300.0},"nxt_expiry":{"expiry_date":"2021-06-24","actual_data_date":"2021-06-24","T_days":45,"entry_ce_premium":1.46,"expiry_close":66.75,"intrinsic_value":26.75,"result":"LOSS","pnl_per_unit":-4.38,"return_pct":-300.0}},{"entry_date":"2021-05-07","expiry_date":"2021-05-27","actual_data_date":"2021-05-27","entry_price":35.15,"surge_high":36.1,"strike":40,"entry_ce_premium":0.69,"expiry_close":46.8,"intrinsic_value":6.8,"iv_sigma":66.4,"T_days":20,"expiry_mode":"auto","expiry_label":"auto","result":"LOSS","pnl_per_unit":-2.07,"return_pct":-300.0,"vol_at_g3":30644550,"avg_vol_20d_g3":8763585,"vol_surge_at_g3":3.5,"premium_score":2.42,"is_high_prem":true,"ticker":"HFCL","gate1_date":"2018-03-22","gate2_date":"2018-03-22","gate3_date":"2021-05-07","surge_gain_pct":21.83,"surge_candles":3,"volume_ratio":0.58,"cur_expiry":{"expiry_date":"2021-05-27","actual_data_date":"2021-05-27","T_days":20,"entry_ce_premium":0.69,"expiry_close":46.8,"intrinsic_value":6.8,"result":"LOSS","pnl_per_unit":-2.07,"return_pct":-300.0},"nxt_expiry":{"expiry_date":"2021-06-24","actual_data_date":"2021-06-24","T_days":48,"entry_ce_premium":1.77,"expiry_close":66.75,"intrinsic_value":26.75,"result":"LOSS","pnl_per_unit":-5.31,"return_pct":-300.0}},{"entry_date":"2018-06-12","expiry_date":"2018-06-28","actual_data_date":"2018-06-28","entry_price":31.85,"surge_high":33.05,"strike":40,"entry_ce_premium":0.01,"expiry_close":27.35,"intrinsic_value":0.0,"iv_sigma":47.5,"T_days":16,"expiry_mode":"auto","expiry_label":"auto","result":"WIN","pnl_per_unit":0.01,"return_pct":100.0,"vol_at_g3":12457791,"avg_vol_20d_g3":6261453,"vol_surge_at_g3":1.99,"premium_score":0.02,"is_high_prem":true,"ticker":"HFCL","gate1_date":"2018-03-28","gate2_date":"2018-03-28","gate3_date":"2018-06-12","surge_gain_pct":21.83,"surge_candles":3,"volume_ratio":0.95,"cur_expiry":{"expiry_date":"2018-06-28","actual_data_date":"2018-06-28","T_days":16,"entry_ce_premium":0.01,"expiry_close":27.35,"intrinsic_value":0.0,"result":"WIN","pnl_per_unit":0.01,"return_pct":100.0},"nxt_expiry":{"expiry_date":"2018-07-26","actual_data_date":"2018-07-26","T_days":44,"entry_ce_premium":0.25,"expiry_close":25.25,"intrinsic_value":0.0,"result":"WIN","pnl_per_unit":0.25,"return_pct":100.0}},{"entry_date":"2021-05-07","expiry_date":"2021-05-27","actual_data_date":"2021-05-27","entry_price":35.15,"surge_high":35.25,"strike":40,"entry_ce_premium":0.69,"expiry_close":46.8,"intrinsic_value":6.8,"iv_sigma":66.4,"T_days":20,"expiry_mode":"auto","expiry_label":"auto","result":"LOSS","pnl_per_unit":-2.07,"return_pct":-300.0,"vol_at_g3":30644550,"avg_vol_20d_g3":8763585,"vol_surge_at_g3":3.5,"premium_score":2.42,"is_high_prem":true,"ticker":"HFCL","gate1_date":"2018-06-21","gate2_date":"2018-06-21","gate3_date":"2021-05-07","surge_gain_pct":39.76,"surge_candles":8,"volume_ratio":1.37,"cur_expiry":{"expiry_date":"2021-05-27","actual_data_date":"2021-05-27","T_days":20,"entry_ce_premium":0.69,"expiry_close":46.8,"intrinsic_value":6.8,"result":"LOSS","pnl_per_unit":-2.07,"return_pct":-300.0},"nxt_expiry":{"expiry_date":"2021-06-24","actual_data_date":"2021-06-24","T_days":48,"entry_ce_premium":1.77,"expiry_close":66.75,"intrinsic_value":26.75,"result":"LOSS","pnl_per_unit":-5.31,"return_pct":-300.0}},{"entry_date":"2020-08-11","expiry_date":"2020-08-27","actual_data_date":"2020-08-27","entry_price":16.55,"surge_high":17.5,"strike":20,"entry_ce_premium":0.15,"expiry_close":17.05,"intrinsic_value":0.0,"iv_sigma":72.6,"T_days":16,"expiry_mode":"auto","expiry_label":"auto","result":"WIN","pnl_per_unit":0.15,"return_pct":100.0,"vol_at_g3":13922729,"avg_vol_20d_g3":3604347,"vol_surge_at_g3":3.86,"premium_score":0.58,"is_high_prem":true,"ticker":"HFCL","gate1_date":"2020-04-20","gate2_date":"2020-04-28","gate3_date":"2020-08-11","surge_gain_pct":32.75,"surge_candles":7,"volume_ratio":0.6,"cur_expiry":{"expiry_date":"2020-08-27","actual_data_date":"2020-08-27","T_days":16,"entry_ce_premium":0.15,"expiry_close":17.05,"intrinsic_value":0.0,"result":"WIN","pnl_per_unit":0.15,"return_pct":100.0},"nxt_expiry":{"expiry_date":"2020-09-24","actual_data_date":"2020-09-24","T_days":44,"entry_ce_premium":0.63,"expiry_close":14.35,"intrinsic_value":0.0,"result":"WIN","pnl_per_unit":0.63,"return_pct":100.0}},{"entry_date":"2021-05-06","expiry_date":"2021-05-27","actual_data_date":"2021-05-27","entry_price":34.0,"surge_high":34.65,"strike":40,"entry_ce_premium":0.48,"expiry_close":46.8,"intrinsic_value":6.8,"iv_sigma":66.0,"T_days":21,"expiry_mode":"auto","expiry_label":"auto","result":"LOSS","pnl_per_unit":-1.44,"return_pct":-300.0,"vol_at_g3":23701284,"avg_vol_20d_g3":7766131,"vol_surge_at_g3":3.05,"premium_score":1.46,"is_high_prem":true,"ticker":"HFCL","gate1_date":"2020-12-30","gate2_date":"2021-01-18","gate3_date":"2021-05-06","surge_gain_pct":36.2,"surge_candles":5,"volume_ratio":0.52,"cur_expiry":{"expiry_date":"2021-05-27","actual_data_date":"2021-05-27","T_days":21,"entry_ce_premium":0.48,"expiry_close":46.8,"intrinsic_value":6.8,"result":"LOSS","pnl_per_unit":-1.44,"return_pct":-300.0},"nxt_expiry":{"expiry_date":"2021-06-24","actual_data_date":"2021-06-24","T_days":49,"entry_ce_premium":1.41,"expiry_close":66.75,"intrinsic_value":26.75,"result":"LOSS","pnl_per_unit":-4.23,"return_pct":-300.0}},{"entry_date":"2021-06-08","expiry_date":"2021-06-24","actual_data_date":"2021-06-24","entry_price":51.15,"surge_high":51.4,"strike":60,"entry_ce_premium":0.89,"expiry_close":66.75,"intrinsic_value":6.75,"iv_sigma":80.8,"T_days":16,"expiry_mode":"auto","expiry_label":"auto","result":"LOSS","pnl_per_unit":-2.67,"return_pct":-300.0,"vol_at_g3":68369442,"avg_vol_20d_g3":43287005,"vol_surge_at_g3":1.58,"premium_score":1.41,"is_high_prem":true,"ticker":"HFCL","gate1_date":"2021-04-29","gate2_date":"2021-06-01","gate3_date":"2021-06-08","surge_gain_pct":19.29,"surge_candles":3,"volume_ratio":0.57,"cur_expiry":{"expiry_date":"2021-06-24","actual_data_date":"2021-06-24","T_days":16,"entry_ce_premium":0.89,"expiry_close":66.75,"intrinsic_value":6.75,"result":"LOSS","pnl_per_unit":-2.67,"return_pct":-300.0},"nxt_expiry":{"expiry_date":"2021-07-29","actual_data_date":"2021-07-29","T_days":51,"entry_ce_premium":3.28,"expiry_close":71.75,"intrinsic_value":11.75,"result":"LOSS","pnl_per_unit":-8.47,"return_pct":-258.2}},{"entry_date":"2021-12-09","expiry_date":"2021-12-30","actual_data_date":"2021-12-30","entry_price":92.4,"surge_high":93.0,"strike":100,"entry_ce_premium":2.91,"expiry_close":78.9,"intrinsic_value":0.0,"iv_sigma":63.4,"T_days":21,"expiry_mode":"auto","expiry_label":"auto","result":"WIN","pnl_per_unit":2.91,"return_pct":100.0,"vol_at_g3":68240661,"avg_vol_20d_g3":12511199,"vol_surge_at_g3":5.45,"premium_score":15.86,"is_high_prem":true,"ticker":"HFCL","gate1_date":"2021-09-16","gate2_date":"2021-09-17","gate3_date":"2021-12-09","surge_gain_pct":21.43,"surge_candles":5,"volume_ratio":1.14,"cur_expiry":{"expiry_date":"2021-12-30","actual_data_date":"2021-12-30","T_days":21,"entry_ce_premium":2.91,"expiry_close":78.9,"intrinsic_value":0.0,"result":"WIN","pnl_per_unit":2.91,"return_pct":100.0},"nxt_expiry":{"expiry_date":"2022-01-27","actual_data_date":"2022-01-27","T_days":49,"entry_ce_premium":5.89,"expiry_close":81.95,"intrinsic_value":0.0,"result":"WIN","pnl_per_unit":5.89,"return_pct":100.0}},{"entry_date":"2021-10-18","expiry_date":"2021-10-28","actual_data_date":"2021-10-28","entry_price":79.0,"surge_high":82.6,"strike":90,"entry_ce_premium":0.11,"expiry_close":72.7,"intrinsic_value":0.0,"iv_sigma":45.5,"T_days":10,"expiry_mode":"auto","expiry_label":"auto","result":"WIN","pnl_per_unit":0.11,"return_pct":100.0,"vol_at_g3":9025802,"avg_vol_20d_g3":4467433,"vol_surge_at_g3":2.02,"premium_score":0.22,"is_high_prem":true,"ticker":"HFCL","gate1_date":"2021-10-08","gate2_date":"2021-10-13","gate3_date":"2021-10-18","surge_gain_pct":21.43,"surge_candles":5,"volume_ratio":1.19,"cur_expiry":{"expiry_date":"2021-10-28","actual_data_date":"2021-10-28","T_days":10,"entry_ce_premium":0.11,"expiry_close":72.7,"intrinsic_value":0.0,"result":"WIN","pnl_per_unit":0.11,"return_pct":100.0},"nxt_expiry":{"expiry_date":"2021-11-25","actual_data_date":"2021-11-25","T_days":38,"entry_ce_premium":1.37,"expiry_close":76.9,"intrinsic_value":0.0,"result":"WIN","pnl_per_unit":1.37,"return_pct":100.0}},{"entry_date":"2021-12-07","expiry_date":"2021-12-30","actual_data_date":"2021-12-30","entry_price":77.85,"surge_high":82.85,"strike":90,"entry_ce_premium":0.95,"expiry_close":78.9,"intrinsic_value":0.0,"iv_sigma":55.5,"T_days":23,"expiry_mode":"auto","expiry_label":"auto","result":"WIN","pnl_per_unit":0.95,"return_pct":100.0,"vol_at_g3":36451021,"avg_vol_20d_g3":7669833,"vol_surge_at_g3":4.75,"premium_score":4.51,"is_high_prem":true,"ticker":"HFCL","gate1_date":"2021-10-19","gate2_date":"2021-10-19","gate3_date":"2021-12-07","surge_gain_pct":21.43,"surge_candles":5,"volume_ratio":1.16,"cur_expiry":{"expiry_date":"2021-12-30","actual_data_date":"2021-12-30","T_days":23,"entry_ce_premium":0.95,"expiry_close":78.9,"intrinsic_value":0.0,"result":"WIN","pnl_per_unit":0.95,"return_pct":100.0},"nxt_expiry":{"expiry_date":"2022-01-27","actual_data_date":"2022-01-27","T_days":51,"entry_ce_premium":2.66,"expiry_close":81.95,"intrinsic_value":0.0,"result":"WIN","pnl_per_unit":2.66,"return_pct":100.0}},{"entry_date":"2022-01-14","expiry_date":"2022-01-27","actual_data_date":"2022-01-27","entry_price":91.85,"surge_high":93.7,"strike":100,"entry_ce_premium":2.1,"expiry_close":81.95,"intrinsic_value":0.0,"iv_sigma":71.0,"T_days":13,"expiry_mode":"auto","expiry_label":"auto","result":"WIN","pnl_per_unit":2.1,"return_pct":100.0,"vol_at_g3":73660895,"avg_vol_20d_g3":17503217,"vol_surge_at_g3":4.21,"premium_score":8.84,"is_high_prem":true,"ticker":"HFCL","gate1_date":"2021-12-14","gate2_date":"2021-12-14","gate3_date":"2022-01-14","surge_gain_pct":32.0,"surge_candles":5,"volume_ratio":2.44,"cur_expiry":{"expiry_date":"2022-01-27","actual_data_date":"2022-01-27","T_days":13,"entry_ce_premium":2.1,"expiry_close":81.95,"intrinsic_value":0.0,"result":"WIN","pnl_per_unit":2.1,"return_pct":100.0},"nxt_expiry":{"expiry_date":"2022-02-24","actual_data_date":"2022-02-24","T_days":41,"entry_ce_premium":5.81,"expiry_close":63.85,"intrinsic_value":0.0,"result":"WIN","pnl_per_unit":5.81,"return_pct":100.0}},{"entry_date":"2024-01-23","expiry_date":"2024-02-29","actual_data_date":"2024-02-29","entry_price":93.65,"surge_high":101.35,"strike":110,"entry_ce_premium":1.76,"expiry_close":107.3,"intrinsic_value":0.0,"iv_sigma":54.2,"T_days":37,"expiry_mode":"auto","expiry_label":"auto","result":"WIN","pnl_per_unit":1.76,"return_pct":100.0,"vol_at_g3":70934276,"avg_vol_20d_g3":37497613,"vol_surge_at_g3":1.89,"premium_score":3.33,"is_high_prem":true,"ticker":"HFCL","gate1_date":"2022-01-11","gate2_date":"2022-01-19","gate3_date":"2024-01-23","surge_gain_pct":32.0,"surge_candles":5,"volume_ratio":0.59,"cur_expiry":null,"nxt_expiry":{"expiry_date":"2024-02-29","actual_data_date":"2024-02-29","T_days":37,"entry_ce_premium":1.76,"expiry_close":107.3,"intrinsic_value":0.0,"result":"WIN","pnl_per_unit":1.76,"return_pct":100.0}},{"entry_date":"2022-12-07","expiry_date":"2022-12-29","actual_data_date":"2022-12-29","entry_price":83.7,"surge_high":86.3,"strike":90,"entry_ce_premium":0.86,"expiry_close":73.55,"intrinsic_value":0.0,"iv_sigma":34.5,"T_days":22,"expiry_mode":"auto","expiry_label":"auto","result":"WIN","pnl_per_unit":0.86,"return_pct":100.0,"vol_at_g3":54227720,"avg_vol_20d_g3":9341970,"vol_surge_at_g3":5.8,"premium_score":4.99,"is_high_prem":true,"ticker":"HFCL","gate1_date":"2022-04-07","gate2_date":"2022-04-12","gate3_date":"2022-12-07","surge_gain_pct":19.26,"surge_candles":6,"volume_ratio":2.02,"cur_expiry":{"expiry_date":"2022-12-29","actual_data_date":"2022-12-29","T_days":22,"entry_ce_premium":0.86,"expiry_close":73.55,"intrinsic_value":0.0,"result":"WIN","pnl_per_unit":0.86,"return_pct":100.0},"nxt_expiry":{"expiry_date":"2023-01-26","actual_data_date":"2023-01-27","T_days":50,"entry_ce_premium":2.18,"expiry_close":67.95,"intrinsic_value":0.0,"result":"WIN","pnl_per_unit":2.18,"return_pct":100.0}},{"entry_date":"2022-09-02","expiry_date":"2022-09-29","actual_data_date":"2022-09-29","entry_price":76.4,"surge_high":78.2,"strike":80,"entry_ce_premium":2.58,"expiry_close":72.4,"intrinsic_value":0.0,"iv_sigma":47.1,"T_days":27,"expiry_mode":"auto","expiry_label":"auto","result":"WIN","pnl_per_unit":2.58,"return_pct":100.0,"vol_at_g3":31331172,"avg_vol_20d_g3":11376723,"vol_surge_at_g3":2.75,"premium_score":7.1,"is_high_prem":true,"ticker":"HFCL","gate1_date":"2022-08-19","gate2_date":"2022-08-19","gate3_date":"2022-09-02","surge_gain_pct":20.05,"surge_candles":4,"volume_ratio":0.86,"cur_expiry":{"expiry_date":"2022-09-29","actual_data_date":"2022-09-29","T_days":27,"entry_ce_premium":2.58,"expiry_close":72.4,"intrinsic_value":0.0,"result":"WIN","pnl_per_unit":2.58,"return_pct":100.0},"nxt_expiry":{"expiry_date":"2022-10-27","actual_data_date":"2022-10-27","T_days":55,"entry_ce_premium":4.36,"expiry_close":78.15,"intrinsic_value":0.0,"result":"WIN","pnl_per_unit":4.36,"return_pct":100.0}},{"entry_date":"2022-10-11","expiry_date":"2022-10-27","actual_data_date":"2022-10-27","entry_price":77.3,"surge_high":82.5,"strike":90,"entry_ce_premium":0.08,"expiry_close":78.15,"intrinsic_value":0.0,"iv_sigma":38.5,"T_days":16,"expiry_mode":"auto","expiry_label":"auto","result":"WIN","pnl_per_unit":0.08,"return_pct":100.0,"vol_at_g3":19629414,"avg_vol_20d_g3":9737612,"vol_surge_at_g3":2.02,"premium_score":0.16,"is_high_prem":true,"ticker":"HFCL","gate1_date":"2022-09-09","gate2_date":"2022-09-13","gate3_date":"2022-10-11","surge_gain_pct":20.05,"surge_candles":4,"volume_ratio":0.78,"cur_expiry":{"expiry_date":"2022-10-27","actual_data_date":"2022-10-27","T_days":16,"entry_ce_premium":0.08,"expiry_close":78.15,"intrinsic_value":0.0,"result":"WIN","pnl_per_unit":0.08,"return_pct":100.0},"nxt_expiry":{"expiry_date":"2022-11-24","actual_data_date":"2022-11-24","T_days":44,"entry_ce_premium":0.79,"expiry_close":79.5,"intrinsic_value":0.0,"result":"WIN","pnl_per_unit":0.79,"return_pct":100.0}},{"entry_date":"2023-09-29","expiry_date":"2023-10-26","actual_data_date":"2023-10-26","entry_price":77.15,"surge_high":80.95,"strike":90,"entry_ce_premium":0.37,"expiry_close":63.35,"intrinsic_value":0.0,"iv_sigma":40.6,"T_days":27,"expiry_mode":"auto","expiry_label":"auto","result":"WIN","pnl_per_unit":0.37,"return_pct":100.0,"vol_at_g3":28070817,"avg_vol_20d_g3":16082291,"vol_surge_at_g3":1.75,"premium_score":0.65,"is_high_prem":true,"ticker":"HFCL","gate1_date":"2023-09-07","gate2_date":"2023-09-12","gate3_date":"2023-09-29","surge_gain_pct":18.34,"surge_candles":6,"volume_ratio":0.59,"cur_expiry":null,"nxt_expiry":{"expiry_date":"2023-10-26","actual_data_date":"2023-10-26","T_days":27,"entry_ce_premium":0.37,"expiry_close":63.35,"intrinsic_value":0.0,"result":"WIN","pnl_per_unit":0.37,"return_pct":100.0}},{"entry_date":"2023-12-18","expiry_date":"2023-12-28","actual_data_date":"2023-12-28","entry_price":78.1,"surge_high":80.95,"strike":90,"entry_ce_premium":0.03,"expiry_close":82.75,"intrinsic_value":0.0,"iv_sigma":38.6,"T_days":10,"expiry_mode":"auto","expiry_label":"auto","result":"WIN","pnl_per_unit":0.03,"return_pct":100.0,"vol_at_g3":117218898,"avg_vol_20d_g3":10252191,"vol_surge_at_g3":11.43,"premium_score":0.34,"is_high_prem":true,"ticker":"HFCL","gate1_date":"2023-10-04","gate2_date":"2023-10-04","gate3_date":"2023-12-18","surge_gain_pct":18.34,"surge_candles":6,"volume_ratio":0.51,"cur_expiry":{"expiry_date":"2023-12-28","actual_data_date":"2023-12-28","T_days":10,"entry_ce_premium":0.03,"expiry_close":82.75,"intrinsic_value":0.0,"result":"WIN","pnl_per_unit":0.03,"return_pct":100.0},"nxt_expiry":{"expiry_date":"2024-01-25","actual_data_date":"2024-01-25","T_days":38,"entry_ce_premium":0.73,"expiry_close":105.75,"intrinsic_value":15.75,"result":"LOSS","pnl_per_unit":-2.19,"return_pct":-300.0}},{"entry_date":"2024-01-23","expiry_date":"2024-02-29","actual_data_date":"2024-02-29","entry_price":93.65,"surge_high":94.65,"strike":100,"entry_ce_premium":4.17,"expiry_close":107.3,"intrinsic_value":7.3,"iv_sigma":54.2,"T_days":37,"expiry_mode":"auto","expiry_label":"auto","result":"LOSS","pnl_per_unit":-3.13,"return_pct":-75.1,"vol_at_g3":70934276,"avg_vol_20d_g3":37497613,"vol_surge_at_g3":1.89,"premium_score":7.88,"is_high_prem":true,"ticker":"HFCL","gate1_date":"2023-12-20","gate2_date":"2024-01-12","gate3_date":"2024-01-23","surge_gain_pct":19.9,"surge_candles":4,"volume_ratio":3.0,"cur_expiry":{"expiry_date":"2024-01-25","actual_data_date":"2024-01-25","T_days":2,"entry_ce_premium":0.08,"expiry_close":105.75,"intrinsic_value":5.75,"result":"LOSS","pnl_per_unit":-0.24,"return_pct":-300.0},"nxt_expiry":{"expiry_date":"2024-02-29","actual_data_date":"2024-02-29","T_days":37,"entry_ce_premium":4.17,"expiry_close":107.3,"intrinsic_value":7.3,"result":"LOSS","pnl_per_unit":-3.13,"return_pct":-75.1}},{"entry_date":"2024-02-08","expiry_date":"2024-02-29","actual_data_date":"2024-02-29","entry_price":107.05,"surge_high":108.8,"strike":110,"entry_ce_premium":4.38,"expiry_close":107.3,"intrinsic_value":0.0,"iv_sigma":53.7,"T_days":21,"expiry_mode":"auto","expiry_label":"auto","result":"WIN","pnl_per_unit":4.38,"return_pct":100.0,"vol_at_g3":77772611,"avg_vol_20d_g3":35328950,"vol_surge_at_g3":2.2,"premium_score":9.64,"is_high_prem":true,"ticker":"HFCL","gate1_date":"2024-01-29","gate2_date":"2024-02-02","gate3_date":"2024-02-08","surge_gain_pct":25.89,"surge_candles":3,"volume_ratio":0.67,"cur_expiry":{"expiry_date":"2024-02-29","actual_data_date":"2024-02-29","T_days":21,"entry_ce_premium":4.38,"expiry_close":107.3,"intrinsic_value":0.0,"result":"WIN","pnl_per_unit":4.38,"return_pct":100.0},"nxt_expiry":{"expiry_date":"2024-03-28","actual_data_date":"2024-03-28","T_days":49,"entry_ce_premium":7.51,"expiry_close":91.8,"intrinsic_value":0.0,"result":"WIN","pnl_per_unit":7.51,"return_pct":100.0}},{"entry_date":"2024-02-20","expiry_date":"2024-02-29","actual_data_date":"2024-02-29","entry_price":110.85,"surge_high":112.45,"strike":120,"entry_ce_premium":1.45,"expiry_close":107.3,"intrinsic_value":0.0,"iv_sigma":63.8,"T_days":9,"expiry_mode":"auto","expiry_label":"auto","result":"WIN","pnl_per_unit":1.45,"return_pct":100.0,"vol_at_g3":85981341,"avg_vol_20d_g3":42572630,"vol_surge_at_g3":2.02,"premium_score":2.93,"is_high_prem":true,"ticker":"HFCL","gate1_date":"2024-02-09","gate2_date":"2024-02-09","gate3_date":"2024-02-20","surge_gain_pct":25.89,"surge_candles":3,"volume_ratio":1.04,"cur_expiry":{"expiry_date":"2024-02-29","actual_data_date":"2024-02-29","T_days":9,"entry_ce_premium":1.45,"expiry_close":107.3,"intrinsic_value":0.0,"result":"WIN","pnl_per_unit":1.45,"return_pct":100.0},"nxt_expiry":{"expiry_date":"2024-03-28","actual_data_date":"2024-03-28","T_days":37,"entry_ce_premium":5.72,"expiry_close":91.8,"intrinsic_value":0.0,"result":"WIN","pnl_per_unit":5.72,"return_pct":100.0}},{"entry_date":"2024-07-05","expiry_date":"2024-07-25","actual_data_date":"2024-07-25","entry_price":130.36,"surge_high":130.5,"strike":140,"entry_ce_premium":6.75,"expiry_close":118.31,"intrinsic_value":0.0,"iv_sigma":85.1,"T_days":20,"expiry_mode":"auto","expiry_label":"auto","result":"WIN","pnl_per_unit":6.75,"return_pct":100.0,"vol_at_g3":81150138,"avg_vol_20d_g3":49887287,"vol_surge_at_g3":1.63,"premium_score":11.0,"is_high_prem":true,"ticker":"HFCL","gate1_date":"2024-06-21","gate2_date":"2024-06-24","gate3_date":"2024-07-05","surge_gain_pct":52.22,"surge_candles":9,"volume_ratio":0.61,"cur_expiry":{"expiry_date":"2024-07-25","actual_data_date":"2024-07-25","T_days":20,"entry_ce_premium":6.75,"expiry_close":118.31,"intrinsic_value":0.0,"result":"WIN","pnl_per_unit":6.75,"return_pct":100.0},"nxt_expiry":{"expiry_date":"2024-08-29","actual_data_date":"2024-08-29","T_days":55,"entry_ce_premium":13.81,"expiry_close":146.79,"intrinsic_value":6.79,"result":"LOSS","pnl_per_unit":7.02,"return_pct":50.8}},{"entry_date":"2024-07-30","expiry_date":"2024-08-29","actual_data_date":"2024-08-29","entry_price":134.81,"surge_high":135.4,"strike":140,"entry_ce_premium":6.07,"expiry_close":146.79,"intrinsic_value":6.79,"iv_sigma":51.7,"T_days":30,"expiry_mode":"auto","expiry_label":"auto","result":"LOSS","pnl_per_unit":-0.72,"return_pct":-11.9,"vol_at_g3":76304970,"avg_vol_20d_g3":36742223,"vol_surge_at_g3":2.08,"premium_score":12.63,"is_high_prem":true,"ticker":"HFCL","gate1_date":"2024-07-09","gate2_date":"2024-07-10","gate3_date":"2024-07-30","surge_gain_pct":52.22,"surge_candles":9,"volume_ratio":0.59,"cur_expiry":{"expiry_date":"2024-07-25","actual_data_date":"2024-07-25","T_days":-5,"entry_ce_premium":0.01,"expiry_close":118.31,"intrinsic_value":0.0,"result":"WIN","pnl_per_unit":0.01,"return_pct":100.0},"nxt_expiry":{"expiry_date":"2024-08-29","actual_data_date":"2024-08-29","T_days":30,"entry_ce_premium":6.07,"expiry_close":146.79,"intrinsic_value":6.79,"result":"LOSS","pnl_per_unit":-0.72,"return_pct":-11.9}},{"entry_date":"2024-08-07","expiry_date":"2024-08-29","actual_data_date":"2024-08-29","entry_price":137.9,"surge_high":140.5,"strike":150,"entry_ce_premium":3.82,"expiry_close":146.79,"intrinsic_value":0.0,"iv_sigma":59.4,"T_days":22,"expiry_mode":"auto","expiry_label":"auto","result":"WIN","pnl_per_unit":3.82,"return_pct":100.0,"vol_at_g3":111529895,"avg_vol_20d_g3":37016796,"vol_surge_at_g3":3.01,"premium_score":11.5,"is_high_prem":true,"ticker":"HFCL","gate1_date":"2024-08-02","gate2_date":"2024-08-05","gate3_date":"2024-08-07","surge_gain_pct":52.22,"surge_candles":9,"volume_ratio":1.14,"cur_expiry":{"expiry_date":"2024-08-29","actual_data_date":"2024-08-29","T_days":22,"entry_ce_premium":3.82,"expiry_close":146.79,"intrinsic_value":0.0,"result":"WIN","pnl_per_unit":3.82,"return_pct":100.0},"nxt_expiry":{"expiry_date":"2024-09-26","actual_data_date":"2024-09-26","T_days":50,"entry_ce_premium":7.88,"expiry_close":154.79,"intrinsic_value":4.79,"result":"LOSS","pnl_per_unit":3.09,"return_pct":39.2}},{"entry_date":"2024-09-18","expiry_date":"2024-09-26","actual_data_date":"2024-09-26","entry_price":157.19,"surge_high":160.66,"strike":170,"entry_ce_premium":1.0,"expiry_close":154.79,"intrinsic_value":0.0,"iv_sigma":51.1,"T_days":8,"expiry_mode":"auto","expiry_label":"auto","result":"WIN","pnl_per_unit":1.0,"return_pct":100.0,"vol_at_g3":73753268,"avg_vol_20d_g3":37622632,"vol_surge_at_g3":1.96,"premium_score":1.96,"is_high_prem":true,"ticker":"HFCL","gate1_date":"2024-09-11","gate2_date":"2024-09-11","gate3_date":"2024-09-18","surge_gain_pct":19.94,"surge_candles":11,"volume_ratio":0.63,"cur_expiry":{"expiry_date":"2024-09-26","actual_data_date":"2024-09-26","T_days":8,"entry_ce_premium":1.0,"expiry_close":154.79,"intrinsic_value":0.0,"result":"WIN","pnl_per_unit":1.0,"return_pct":100.0},"nxt_expiry":{"expiry_date":"2024-10-31","actual_data_date":"2024-10-31","T_days":43,"entry_ce_premium":6.55,"expiry_close":121.69,"intrinsic_value":0.0,"result":"WIN","pnl_per_unit":6.55,"return_pct":100.0}},{"entry_date":"2025-06-06","expiry_date":"2025-06-26","actual_data_date":"2025-06-26","entry_price":91.42,"surge_high":92.65,"strike":100,"entry_ce_premium":1.51,"expiry_close":87.52,"intrinsic_value":0.0,"iv_sigma":50.1,"T_days":20,"expiry_mode":"auto","expiry_label":"auto","result":"WIN","pnl_per_unit":1.51,"return_pct":100.0,"vol_at_g3":54799698,"avg_vol_20d_g3":22307823,"vol_surge_at_g3":2.46,"premium_score":3.71,"is_high_prem":true,"ticker":"HFCL","gate1_date":"2025-05-20","gate2_date":"2025-05-21","gate3_date":"2025-06-06","surge_gain_pct":21.5,"surge_candles":5,"volume_ratio":1.74,"cur_expiry":{"expiry_date":"2025-06-26","actual_data_date":"2025-06-26","T_days":20,"entry_ce_premium":1.51,"expiry_close":87.52,"intrinsic_value":0.0,"result":"WIN","pnl_per_unit":1.51,"return_pct":100.0},"nxt_expiry":{"expiry_date":"2025-07-31","actual_data_date":"2025-07-31","T_days":55,"entry_ce_premium":4.18,"expiry_close":75.57,"intrinsic_value":0.0,"result":"WIN","pnl_per_unit":4.18,"return_pct":100.0}},{"entry_date":"2026-03-12","expiry_date":"2026-03-26","actual_data_date":"2026-03-27","entry_price":74.47,"surge_high":75.4,"strike":80,"entry_ce_premium":0.53,"expiry_close":70.76,"intrinsic_value":0.0,"iv_sigma":37.6,"T_days":14,"expiry_mode":"auto","expiry_label":"auto","result":"WIN","pnl_per_unit":0.53,"return_pct":100.0,"vol_at_g3":60068640,"avg_vol_20d_g3":15759565,"vol_surge_at_g3":3.81,"premium_score":2.02,"is_high_prem":true,"ticker":"HFCL","gate1_date":"2026-02-23","gate2_date":"2026-02-23","gate3_date":"2026-03-12","surge_gain_pct":18.62,"surge_candles":8,"volume_ratio":0.64,"cur_expiry":{"expiry_date":"2026-03-26","actual_data_date":"2026-03-27","T_days":14,"entry_ce_premium":0.53,"expiry_close":70.76,"intrinsic_value":0.0,"result":"WIN","pnl_per_unit":0.53,"return_pct":100.0},"nxt_expiry":{"expiry_date":"2026-04-30","actual_data_date":"2026-04-30","T_days":49,"entry_ce_premium":2.24,"expiry_close":116.03,"intrinsic_value":36.03,"result":"LOSS","pnl_per_unit":-6.72,"return_pct":-300.0}}]}],"from_cache":false,"cached_at":"2026-06-05 12:39:19 IST"}